diffuse/__init__.py
diffuse/diffuser/__init__.py
diffuse/diffuser/async_diffuser.py
diffuse/diffuser/base.py
diffuse/diffuser/process.py
diffuse/diffuser/tests/__init__.py
diffuse/diffuser/tests/base.py
diffuse/diffuser/tests/test_async_diffuser.py
diffuse/diffuser/tests/test_common.py
diffuse/diffuser/tests/test_process_diffuser.py
diffuse/diffuser/tests/test_thread_diffuser.py
diffuse/diffuser/thread.py
diffuse/pool.py
diffuse/tests/__init__.py
diffuse/tests/test_pool.py
diffuse/worker/__init__.py
diffuse/worker/async_worker.py
diffuse/worker/base.py
diffuse/worker/process.py
diffuse/worker/tests/__init__.py
diffuse/worker/tests/test_async_worker.py
diffuse/worker/tests/test_process_worker.py
diffuse/worker/tests/test_thread_worker.py
diffuse/worker/thread.py
diffuse-0.3.1.dist-info/LICENSE
diffuse-0.3.1.dist-info/METADATA
diffuse-0.3.1.dist-info/WHEEL
diffuse-0.3.1.dist-info/RECORD
