Metadata-Version: 2.1
Name: diffuse
Version: 0.3.1
Summary: Python Diffuse
Home-page: https://asandeep.github.io/diffuse/
License: MIT
Keywords: python3,concurrency,asyncio,threading,multiprocessing
Author: Sandeep Aggarwal
Author-email: asandeep.me@gmail.com
Requires-Python: >=3.8,<4.0
Classifier: Development Status :: 4 - Beta
Classifier: Framework :: AsyncIO
Classifier: Intended Audience :: Developers
Classifier: License :: OSI Approved :: MIT License
Classifier: Programming Language :: Python :: 3
Classifier: Programming Language :: Python :: 3.8
Classifier: Programming Language :: Python :: 3.9
Classifier: Programming Language :: Python :: 3.10
Classifier: Programming Language :: Python :: 3.11
Classifier: Programming Language :: Python :: 3.12
Classifier: Topic :: Software Development :: Libraries :: Python Modules
Project-URL: Repository, https://github.com/asandeep/diffuse.git
